odoo/addons/website_membership_gamification/README.rst
odoo/addons/website_membership_gamification/__init__.py
odoo/addons/website_membership_gamification/__manifest__.py
odoo/addons/website_membership_gamification/i18n/es.po
odoo/addons/website_membership_gamification/i18n/fr.po
odoo/addons/website_membership_gamification/i18n/it.po
odoo/addons/website_membership_gamification/i18n/website_membership_gamification.pot
odoo/addons/website_membership_gamification/models/__init__.py
odoo/addons/website_membership_gamification/models/gamification_badge.py
odoo/addons/website_membership_gamification/models/res_partner.py
odoo/addons/website_membership_gamification/readme/CONFIGURE.md
odoo/addons/website_membership_gamification/readme/CONTRIBUTORS.md
odoo/addons/website_membership_gamification/readme/DESCRIPTION.md
odoo/addons/website_membership_gamification/readme/USAGE.md
odoo/addons/website_membership_gamification/static/description/icon.png
odoo/addons/website_membership_gamification/static/description/index.html
odoo/addons/website_membership_gamification/views/badge.xml
odoo/addons/website_membership_gamification/views/res_partner_views.xml
odoo/addons/website_membership_gamification/views/website_partner_template.xml
odoo/addons/website_membership_gamification/wizard/gamification_badge_user_wizard.xml
odoo_addon_website_membership_gamification-18.0.1.0.0.2.dist-info/METADATA
odoo_addon_website_membership_gamification-18.0.1.0.0.2.dist-info/WHEEL
odoo_addon_website_membership_gamification-18.0.1.0.0.2.dist-info/top_level.txt
odoo_addon_website_membership_gamification-18.0.1.0.0.2.dist-info/RECORD
