Metadata-Version: 2.1
Name: odoo-addon-website_membership_gamification
Version: 18.0.1.0.0.2
Requires-Python: >=3.10
Requires-Dist: odoo==18.0.*
Summary: Show badges assigned to users on website
Home-page: https://github.com/OCA/vertical-association
License: AGPL-3
Author: Sygel, Odoo Community Association (OCA)
Author-email: support@odoo-community.org
Classifier: Programming Language :: Python
Classifier: Framework :: Odoo
Classifier: Framework :: Odoo :: 18.0
Classifier: License :: OSI Approved :: GNU Affero General Public License v3
Classifier: Development Status :: 4 - Beta
